streamlit_hub/__init__.py
streamlit_hub/access/__init__.py
streamlit_hub/access/nginx_access.py
streamlit_hub/access/registered_apps_access.py
streamlit_hub/access/repo_access.py
streamlit_hub/client/__init__.py
streamlit_hub/client/app.py
streamlit_hub/client/config.py
streamlit_hub/client/edit_local_app.py
streamlit_hub/client/main.py
streamlit_hub/client/register.py
streamlit_hub/client/status.py
streamlit_hub/manager/__init__.py
streamlit_hub/manager/manager.py
streamlit_hub/models/App.py
streamlit_hub/models/RunningProcess.py
streamlit_hub/models/__init__.py
streamlit_hub-0.3.1.dist-info/LICENSE.txt
streamlit_hub-0.3.1.dist-info/METADATA
streamlit_hub-0.3.1.dist-info/WHEEL
streamlit_hub-0.3.1.dist-info/entry_points.txt
streamlit_hub-0.3.1.dist-info/top_level.txt
streamlit_hub-0.3.1.dist-info/RECORD
