Metadata-Version: 2.1
Name: streamlit-hub
Version: 0.3.1
Summary: Manage your streamlit applciations!
Home-page: https://github.com/pyscaffold/pyscaffold/
Author: Guillaume Moesching
Author-email: guillaume.mosching@gmail.com
License: MIT
Project-URL: Documentation, https://github.com/galaplexus/streamlit-hub
Platform: any
Classifier: Development Status :: 4 - Beta
Classifier: Programming Language :: Python
License-File: LICENSE.txt
Requires-Dist: streamlit >=1.29.0
Requires-Dist: colorlog
Requires-Dist: python-nginx
Requires-Dist: importlib-metadata ; python_version < "3.8"
Provides-Extra: testing
Requires-Dist: setuptools ; extra == 'testing'
Requires-Dist: pytest ; extra == 'testing'
Requires-Dist: pytest-cov ; extra == 'testing'
